{
  "name": "All Pages",
  "category": "Behavior",
  "metrics": [
    "newUsers",
    "percentNewSessions",
    "sessions",
    "bounceRate",
    "avgSessionDuration",
    "pageviews",
    "transactions",
    "transactionRevenue"
  ],
  "dimensions": [
    "landingPagePath",
    "date"
  ],
  "filterOperator": "AND",
  "filters": [
    {
      "dimension": "landingPagePath",
      "operator": "EXACT",
      "expressions": "/",
      "not": "TRUE"
    },
    {
      "dimension": "landingPagePath",
      "operator": "BEGINS_WITH",
      "expressions": "/?",
      "not": "TRUE"
    }
  ]
}